[{"login":"amoussai","campusId":16,"position":1},{"login":"testingg","campusId":16,"position":2},{"login":"sel-jala","campusId":16,"position":2},{"login":"hherba","campusId":16,"position":2},{"login":"magbalou","campusId":16,"position":2},{"login":"megrisse","campusId":16,"position":2},{"login":"ywadday","campusId":16,"position":2},{"login":"iraqi","campusId":16,"position":2},{"login":"yammari","campusId":16,"position":2},{"login":"flazerak","campusId":16,"position":3},{"login":"hghallam","campusId":16,"position":3},{"login":"yelousse","campusId":16,"position":3},{"login":"hchahid","campusId":16,"position":3},{"login":"mzridi","campusId":16,"position":3},{"login":"iassim","campusId":16,"position":3},{"login":"yait-ouc","campusId":16,"position":3},{"login":"zcherrad","campusId":16,"position":3},{"login":"mboumra","campusId":16,"position":3},{"login":"hnabil","campusId":16,"position":3},{"login":"hrajad","campusId":16,"position":3},{"login":"fabou-za","campusId":16,"position":3},{"login":"yait-kad","campusId":16,"position":3},{"login":"eaouassa","campusId":16,"position":4},{"login":"amounach","campusId":16,"position":4},{"login":"ahinani","campusId":16,"position":4},{"login":"yjarhbou","campusId":16,"position":4},{"login":"rnabil","campusId":16,"position":4},{"login":"mouarsas","campusId":16,"position":4},{"login":"achafi","campusId":16,"position":4},{"login":"mbouthai","campusId":16,"position":4},{"login":"eelhasni","campusId":16,"position":4},{"login":"aelissao","campusId":16,"position":4},{"login":"obounri","campusId":16,"position":4},{"login":"ssadiki","campusId":16,"position":5},{"login":"tallam","campusId":16,"position":5},{"login":"ylaagaou","campusId":16,"position":5},{"login":"yhmada","campusId":16,"position":5},{"login":"aechafii","campusId":16,"position":5},{"login":"hel-hadd","campusId":16,"position":5},{"login":"abdel-ke","campusId":16,"position":5},{"login":"zlayine","campusId":16,"position":5},{"login":"abbelhac","campusId":16,"position":5},{"login":"iltafah","campusId":16,"position":5},{"login":"zjamali","campusId":16,"position":5},{"login":"omouhtal","campusId":16,"position":6},{"login":"aoustani","campusId":16,"position":6},{"login":"anaciri","campusId":16,"position":6},{"login":"aes-slim","campusId":16,"position":6},{"login":"akouame","campusId":16,"position":6},{"login":"hbenzzin","campusId":16,"position":6},{"login":"tbouzalm","campusId":16,"position":6},{"login":"mboulano","campusId":16,"position":6},{"login":"shafsi","campusId":16,"position":6},{"login":"abazizi","campusId":16,"position":6},{"login":"aboumadi","campusId":16,"position":6},{"login":"mwahbi","campusId":16,"position":6},{"login":"mbouazza","campusId":16,"position":6},{"login":"irachyq","campusId":16,"position":6},{"login":"ybahmane","campusId":16,"position":6},{"login":"abouksim","campusId":16,"position":6},{"login":"makacem","campusId":16,"position":6},{"login":"hel-ayac","campusId":16,"position":6},{"login":"asfaihi","campusId":16,"position":6},{"login":"nmoussam","campusId":16,"position":6},{"login":"cabouelw","campusId":16,"position":6},{"login":"amrakibe","campusId":16,"position":7},{"login":"cel-fita","campusId":16,"position":7},{"login":"yel-khad","campusId":16,"position":7},{"login":"mlalouli","campusId":16,"position":7},{"login":"nbouljih","campusId":16,"position":7},{"login":"ylaarous","campusId":16,"position":7},{"login":"ilahyani","campusId":16,"position":7},{"login":"iel-moun","campusId":16,"position":7},{"login":"abelahce","campusId":16,"position":7},{"login":"mnajid","campusId":16,"position":7},{"login":"azouaiga","campusId":16,"position":7},{"login":"rel-maza","campusId":16,"position":7},{"login":"mbari","campusId":16,"position":7},{"login":"amouassi","campusId":16,"position":7},{"login":"ychennaf","campusId":16,"position":7},{"login":"abkssiba","campusId":16,"position":7},{"login":"oakoudad","campusId":16,"position":8},{"login":"mnachit","campusId":16,"position":8},{"login":"hkaddour","campusId":16,"position":8},{"login":"aabdelad","campusId":16,"position":8},{"login":"ahammout","campusId":16,"position":8},{"login":"achahid","campusId":16,"position":8},{"login":"kbadr","campusId":16,"position":8},{"login":"mhamdani","campusId":16,"position":8},{"login":"lahammam","campusId":16,"position":8},{"login":"eal-dris","campusId":16,"position":8},{"login":"iqabbal","campusId":16,"position":8},{"login":"zghouzla","campusId":16,"position":8},{"login":"cbourajl","campusId":16,"position":8},{"login":"hameur","campusId":16,"position":8},{"login":"yel-mekk","campusId":16,"position":8},{"login":"yrahmoun","campusId":16,"position":8},{"login":"fael-bou","campusId":16,"position":8},{"login":"bibrahim","campusId":16,"position":8},{"login":"mmakboub","campusId":16,"position":8},{"login":"aidouiss","campusId":16,"position":8},{"login":"mfallahi","campusId":16,"position":8},{"login":"zmoussam","campusId":16,"position":8},{"login":"iel-fati","campusId":16,"position":8},{"login":"kel-alam","campusId":16,"position":8},{"login":"kel-amra","campusId":16,"position":8},{"login":"adaifi","campusId":16,"position":8},{"login":"ielmakhf","campusId":16,"position":8},{"login":"isel-jao","campusId":16,"position":8},{"login":"yqodsi","campusId":16,"position":8},{"login":"aboulbaz","campusId":16,"position":8},{"login":"yoelhaim","campusId":16,"position":9},{"login":"abziouzi","campusId":16,"position":9},{"login":"aboubche","campusId":16,"position":9},{"login":"zcherkao","campusId":16,"position":9},{"login":"anaji-el","campusId":16,"position":9},{"login":"ederkaou","campusId":16,"position":9},{"login":"yettoumi","campusId":16,"position":9},{"login":"alfertah","campusId":16,"position":9},{"login":"ykhadiri","campusId":16,"position":9},{"login":"abel-oua","campusId":16,"position":9},{"login":"zel-hach","campusId":16,"position":9},{"login":"aadnane","campusId":16,"position":9},{"login":"hbouqssi","campusId":16,"position":9},{"login":"sismaili","campusId":16,"position":9},{"login":"nfatri","campusId":16,"position":9},{"login":"mjalloul","campusId":16,"position":9},{"login":"yamzil","campusId":16,"position":9},{"login":"arouzen","campusId":16,"position":9},{"login":"hboumahd","campusId":16,"position":9},{"login":"moulmado","campusId":16,"position":9},{"login":"hjabbour","campusId":16,"position":9},{"login":"kmabrouk","campusId":16,"position":9},{"login":"ikharbac","campusId":16,"position":9},{"login":"skasmi","campusId":16,"position":9},{"login":"babkar","campusId":16,"position":9},{"login":"aelyakou","campusId":16,"position":9},{"login":"mel-behc","campusId":16,"position":9},{"login":"ygbouri","campusId":16,"position":9},{"login":"hel-moud","campusId":16,"position":9},{"login":"amsenhaj","campusId":16,"position":9},{"login":"ahel-bah","campusId":16,"position":9},{"login":"waelhamd","campusId":16,"position":9},{"login":"net-touz","campusId":16,"position":9},{"login":"kfaouzi","campusId":16,"position":9},{"login":"hmokhtar","campusId":16,"position":9},{"login":"moseddik","campusId":16,"position":9},{"login":"mmeziani","campusId":16,"position":9},{"login":"mbaazzy","campusId":16,"position":9},{"login":"hel-hich","campusId":16,"position":9},{"login":"kabourad","campusId":16,"position":9},{"login":"youchenn","campusId":16,"position":9},{"login":"ibenmain","campusId":16,"position":9},{"login":"ssabbaji","campusId":16,"position":10},{"login":"nouahhab","campusId":16,"position":10},{"login":"yel-qabl","campusId":16,"position":10},{"login":"shbi","campusId":16,"position":10},{"login":"yaskour","campusId":16,"position":10},{"login":"skarem","campusId":16,"position":10},{"login":"oalaoui-","campusId":16,"position":10},{"login":"mhafdi","campusId":16,"position":10},{"login":"orekabe","campusId":16,"position":10},{"login":"souchen","campusId":16,"position":10},{"login":"yghari","campusId":16,"position":10},{"login":"mjlem","campusId":16,"position":10},{"login":"sgmira","campusId":16,"position":10},{"login":"nhanafi","campusId":16,"position":10},{"login":"faljaoui","campusId":16,"position":10},{"login":"vkanate","campusId":16,"position":10},{"login":"wzouf","campusId":16,"position":10},{"login":"rel-hach","campusId":16,"position":10},{"login":"ariahi","campusId":16,"position":10},{"login":"mes-sadk","campusId":16,"position":10},{"login":"zaabou","campusId":16,"position":10},{"login":"ybouddou","campusId":16,"position":10},{"login":"yabdelgh","campusId":16,"position":10},{"login":"iounejja","campusId":16,"position":10},{"login":"imannouc","campusId":16,"position":10},{"login":"oqatim","campusId":16,"position":11},{"login":"ozahid-","campusId":16,"position":11},{"login":"mmohamme","campusId":16,"position":11},{"login":"eseiv","campusId":16,"position":11},{"login":"rjaanit","campusId":16,"position":11},{"login":"mattif","campusId":16,"position":11},{"login":"zhaddoum","campusId":16,"position":11},{"login":"bmaaqoul","campusId":16,"position":11},{"login":"sel-kham","campusId":16,"position":11},{"login":"ikoukou","campusId":16,"position":11},{"login":"ylazrek","campusId":16,"position":11},{"login":"olahbabi","campusId":16,"position":12},{"login":"yismaili","campusId":16,"position":12},{"login":"zmaziane","campusId":16,"position":12},{"login":"abouazi","campusId":16,"position":12},{"login":"arharif","campusId":16,"position":12},{"login":"zzirh","campusId":16,"position":12},{"login":"ibouhlal","campusId":16,"position":12},{"login":"amessah","campusId":16,"position":12},{"login":"yabtaour","campusId":16,"position":12},{"login":"nattia","campusId":16,"position":12},{"login":"rgatnaou","campusId":16,"position":12},{"login":"tel-mouh","campusId":16,"position":12},{"login":"iayni","campusId":16,"position":12},{"login":"ylakhoua","campusId":16,"position":12},{"login":"mcherki","campusId":16,"position":12},{"login":"fel-boua","campusId":16,"position":12},{"login":"aberdai","campusId":16,"position":12},{"login":"mberri","campusId":16,"position":13},{"login":"yhammani","campusId":16,"position":13},{"login":"stamim","campusId":16,"position":13},{"login":"iqessam","campusId":16,"position":13},{"login":"aelousse","campusId":16,"position":13},{"login":"msaoud","campusId":16,"position":13},{"login":"sayar","campusId":16,"position":13},{"login":"obelkhad","campusId":16,"position":13},{"login":"ochoumou","campusId":16,"position":13},{"login":"messalih","campusId":16,"position":13},{"login":"amasnaou","campusId":16,"position":13},{"login":"hadaoud","campusId":16,"position":13},{"login":"mzarhou","campusId":16,"position":14},{"login":"fech-cha","campusId":16,"position":14},{"login":"mazhari","campusId":16,"position":14},{"login":"mazzouzi","campusId":16,"position":14},{"login":"machlouj","campusId":16,"position":14},{"login":"zsarir","campusId":16,"position":14},{"login":"imittous","campusId":16,"position":14},{"login":"rnaamaou","campusId":16,"position":14},{"login":"ajaidi","campusId":16,"position":14},{"login":"ebouabba","campusId":16,"position":14},{"login":"ahazim","campusId":16,"position":14},{"login":"mnesfane","campusId":16,"position":14},{"login":"ymoutaou","campusId":16,"position":14},{"login":"mmessaou","campusId":16,"position":14},{"login":"aait-oma","campusId":16,"position":14},{"login":"atabiti","campusId":16,"position":14},{"login":"btaha","campusId":16,"position":14},{"login":"eel-moun","campusId":16,"position":14},{"login":"amarzoug","campusId":16,"position":14},{"login":"mel-hous","campusId":16,"position":15},{"login":"mbjaghou","campusId":16,"position":15},{"login":"rsaf","campusId":16,"position":15},{"login":"azouaghi","campusId":16,"position":15},{"login":"youssama","campusId":16,"position":15},{"login":"oufisaou","campusId":16,"position":15},{"login":"ooumlil","campusId":16,"position":15},{"login":"ntanjaou","campusId":16,"position":15},{"login":"hlalouli","campusId":16,"position":15},{"login":"hbadr","campusId":16,"position":15},{"login":"nerraou","campusId":16,"position":15},{"login":"yelatman","campusId":16,"position":15},{"login":"mabdelba","campusId":16,"position":15},{"login":"schahid","campusId":16,"position":15},{"login":"asalek","campusId":16,"position":15}]